telegrify/__init__.py
telegrify/__version__.py
telegrify/cli/__init__.py
telegrify/cli/commands.py
telegrify/core/__init__.py
telegrify/core/bot.py
telegrify/core/config.py
telegrify/core/interfaces.py
telegrify/core/registry.py
telegrify/formatters/__init__.py
telegrify/formatters/base.py
telegrify/formatters/markdown.py
telegrify/formatters/plain.py
telegrify/server/__init__.py
telegrify/server/app.py
telegrify/server/routes.py
telegrify/utils/__init__.py
telegrify/utils/escape.py
telegrify/utils/validators.py
telegrify-1.0.5.dist-info/licenses/LICENSE
telegrify-1.0.5.dist-info/METADATA
telegrify-1.0.5.dist-info/WHEEL
telegrify-1.0.5.dist-info/entry_points.txt
telegrify-1.0.5.dist-info/top_level.txt
telegrify-1.0.5.dist-info/RECORD
