Metadata-Version: 2.4
Name: telegrify
Version: 1.0.5
Summary: Simple Telegram notification framework with plugin support
Author-email: Gemechis Chala <gladsonchala@gmail.com>
License: MIT
Project-URL: Homepage, https://github.com/venopyx/telegrify
Project-URL: Repository, https://github.com/venopyx/telegrify
Project-URL: Documentation, https://github.com/venopyx/telegrify#readme
Keywords: telegram,notifications,bot,webhook,fastapi,async
Classifier: Development Status :: 5 - Production/Stable
Classifier: Intended Audience :: Developers
Classifier: License :: OSI Approved :: MIT License
Classifier: Programming Language :: Python :: 3.10
Classifier: Programming Language :: Python :: 3.11
Classifier: Programming Language :: Python :: 3.12
Classifier: Framework :: FastAPI
Classifier: Topic :: Communications :: Chat
Classifier: Topic :: Software Development :: Libraries :: Python Modules
Classifier: Typing :: Typed
Requires-Python: >=3.10
License-File: LICENSE
Requires-Dist: fastapi>=0.104.0
Requires-Dist: pydantic>=2.5.0
Requires-Dist: pydantic-settings>=2.1.0
Requires-Dist: aiohttp>=3.9.0
Requires-Dist: uvicorn[standard]>=0.30.0
Requires-Dist: pyyaml>=6.0
Requires-Dist: jinja2>=3.1.0
Requires-Dist: python-dotenv>=1.0.0
Requires-Dist: click>=8.1.0
Provides-Extra: dev
Requires-Dist: pytest>=7.4.0; extra == "dev"
Requires-Dist: pytest-asyncio>=0.21.0; extra == "dev"
Requires-Dist: pytest-cov>=4.1.0; extra == "dev"
Requires-Dist: black>=23.11.0; extra == "dev"
Requires-Dist: ruff>=0.1.6; extra == "dev"
Requires-Dist: mypy>=1.7.0; extra == "dev"
Requires-Dist: build>=1.0.0; extra == "dev"
Requires-Dist: twine>=4.0.0; extra == "dev"
Dynamic: license-file
